{"Order ID": {"unique_count": 145, "top_values": {"SA-2011-1830": 8, "ID-2011-43977": 8, "ES-2011-2272875": 7, "TU-2011-8780": 7, "CA-2011-110786": 7}}, "Ship Mode": {"unique_count": 4, "top_values": {"Standard Class": 148, "Second Class": 88, "First Class": 55, "Same Day": 14}}, "Customer ID": {"unique_count": 132, "top_values": {"AJ-10795": 10, "RR-19525": 10, "MM-7260": 8, "CM-12115": 8, "LO-7170": 8}}, "Customer Name": {"unique_count": 131, "top_values": {"Anthony Johnson": 10, "Rick Reed": 10, "Magdelene Morse": 8, "Lori Olson": 8, "Chad McGuire": 8}}, "Segment": {"unique_count": 3, "top_values": {"Consumer": 138, "Corporate": 114, "Home Office": 53}}, "City": {"unique_count": 127, "top_values": {"Santo Domingo": 10, "San Francisco": 9, "Philadelphia": 9, "Jizan": 8, "Ho Chi Minh City": 8}}, "State": {"unique_count": 101, "top_values": {"California": 20, "Santo Domingo": 10, "Ile-de-France": 10, "Pennsylvania": 9, "Bahia": 9}}, "Country": {"unique_count": 46, "top_values": {"United States": 80, "Brazil": 22, "France": 13, "India": 11, "Mexico": 11}}, "Market": {"unique_count": 6, "top_values": {"US": 80, "LATAM": 64, "EU": 55, "APAC": 47, "EMEA": 38}}, "Region": {"unique_count": 12, "top_values": {"Central": 67, "South": 39, "EMEA": 38, "West": 30, "East": 29}}, "Product ID": {"unique_count": 299, "top_values": {"OFF-BI-10000340": 3, "OFF-AR-10000176": 2, "OFF-ENE-10001906": 2, "OFF-ROG-10002682": 2, "FUR-BO-10004425": 2}}, "Category": {"unique_count": 3, "top_values": {"Office Supplies": 172, "Technology": 71, "Furniture": 62}}, "Sub-Category": {"unique_count": 17, "top_values": {"Binders": 34, "Storage": 31, "Phones": 29, "Art": 25, "Accessories": 24}}, "Product Name": {"unique_count": 277, "top_values": {"Staples": 5, "Avery Binding Machine, Clear": 3, "Rogers Box, Industrial": 2, "Apple Speaker Phone, Cordless": 2, "BIC Pencil Sharpener, Water Color": 2}}, "Order Priority": {"unique_count": 4, "top_values": {"Medium": 150, "High": 86, "Critical": 48, "Low": 21}}}