{"Order ID": {"unique_count": 189, "top_values": {"MX-2014-166541": 13, "IN-2014-15263": 12, "SF-2014-3260": 11, "US-2014-162558": 7, "IN-2014-43039": 7}}, "Ship Mode": {"unique_count": 4, "top_values": {"Standard Class": 227, "First Class": 69, "Second Class": 64, "Same Day": 22}}, "Customer ID": {"unique_count": 170, "top_values": {"BE-11335": 15, "PO-18850": 15, "LT-7110": 13, "MG-17680": 13, "Dp-13240": 11}}, "Customer Name": {"unique_count": 164, "top_values": {"Patrick O'Brill": 15, "Bill Eplett": 15, "Liz Thompson": 13, "Maureen Gastineau": 13, "Dean percer": 11}}, "Segment": {"unique_count": 3, "top_values": {"Consumer": 176, "Home Office": 126, "Corporate": 80}}, "City": {"unique_count": 158, "top_values": {"Ju\u00e1rez": 17, "Liaocheng": 12, "Pretoria": 11, "Seattle": 9, "Knoxville": 7}}, "State": {"unique_count": 120, "top_values": {"California": 19, "Chihuahua": 17, "Shandong": 13, "Gauteng": 11, "New York": 10}}, "Country": {"unique_count": 50, "top_values": {"United States": 86, "Mexico": 37, "China": 28, "Brazil": 19, "Turkey": 15}}, "Market": {"unique_count": 6, "top_values": {"LATAM": 99, "APAC": 86, "US": 86, "EMEA": 51, "EU": 38}}, "Region": {"unique_count": 12, "top_values": {"Central": 65, "EMEA": 51, "South": 48, "North": 42, "West": 38}}, "Product ID": {"unique_count": 377, "top_values": {"FUR-SAU-10000893": 2, "TEC-MA-10002874": 2, "OFF-IBI-10000779": 2, "TEC-PH-10001063": 2, "TEC-PH-10004358": 2}}, "Category": {"unique_count": 3, "top_values": {"Office Supplies": 218, "Technology": 82, "Furniture": 82}}, "Sub-Category": {"unique_count": 17, "top_values": {"Binders": 54, "Furnishings": 32, "Paper": 29, "Phones": 27, "Storage": 25}}, "Product Name": {"unique_count": 345, "top_values": {"Ibico Index Tab, Economy": 4, "Rogers Shelving, Wire Frame": 3, "Staples": 3, "Acco Binding Machine, Clear": 3, "Samsung Speaker Phone, Full Size": 3}}, "Order Priority": {"unique_count": 4, "top_values": {"Medium": 196, "High": 132, "Critical": 28, "Low": 26}}}