{"Order ID": {"unique_count": 58, "top_values": {"IN-2012-40029": 10, "US-2012-142699": 7, "IN-2012-43165": 5, "ES-2012-2756176": 4, "IN-2012-35143": 4}}, "Ship Mode": {"unique_count": 4, "top_values": {"Standard Class": 73, "Second Class": 23, "First Class": 10, "Same Day": 8}}, "Customer ID": {"unique_count": 57, "top_values": {"MY-18295": 10, "BS-11365": 7, "MM-17260": 5, "RA-19885": 4, "RO-19780": 4}}, "Customer Name": {"unique_count": 57, "top_values": {"Muhammed Yedwab": 10, "Bill Shonely": 7, "Magdelene Morse": 5, "Ruben Ausman": 4, "Rose O'Brian": 4}}, "Segment": {"unique_count": 3, "top_values": {"Consumer": 62, "Corporate": 36, "Home Office": 16}}, "City": {"unique_count": 54, "top_values": {"Xichang": 10, "Portmore": 7, "Puducherry": 6, "Vienna": 5, "Hamburg": 4}}, "State": {"unique_count": 50, "top_values": {"Sichuan": 10, "Saint Catherine": 7, "Puducherry": 6, "Vienna": 5, "Hamburg": 4}}, "Country": {"unique_count": 30, "top_values": {"China": 11, "India": 11, "United States": 9, "Austria": 7, "Jamaica": 7}}, "Market": {"unique_count": 6, "top_values": {"APAC": 40, "EU": 29, "LATAM": 16, "EMEA": 15, "US": 9}}, "Region": {"unique_count": 12, "top_values": {"Central": 20, "South": 15, "EMEA": 15, "Central Asia": 11, "Oceania": 11}}, "Product ID": {"unique_count": 114, "top_values": {"FUR-TA-10000198": 1, "OFF-FA-10000631": 1, "OFF-BI-10003025": 1, "OFF-BOS-10004262": 1, "OFF-SU-10001868": 1}}, "Category": {"unique_count": 3, "top_values": {"Office Supplies": 65, "Technology": 27, "Furniture": 22}}, "Sub-Category": {"unique_count": 17, "top_values": {"Binders": 16, "Art": 12, "Storage": 11, "Chairs": 11, "Supplies": 11}}, "Product Name": {"unique_count": 113, "top_values": {"Hon Rocking Chair, Adjustable": 2, "Chromcraft Bull-Nose Wood Oval Conference Tables & Bases": 1, "Smead Shelving, Industrial": 1, "KitchenAid Coffee Grinder, White": 1, "Cardinal Binding Machine, Durable": 1}}, "Order Priority": {"unique_count": 4, "top_values": {"Medium": 76, "High": 28, "Critical": 7, "Low": 3}}}