{"Order ID": {"unique_count": 45, "top_values": {"IN-2011-81833": 6, "IN-2011-56990": 5, "MO-2011-4320": 5, "SF-2011-2090": 4, "ES-2011-3188488": 4}}, "Ship Mode": {"unique_count": 4, "top_values": {"Standard Class": 45, "Second Class": 28, "First Class": 15, "Same Day": 2}}, "Customer ID": {"unique_count": 45, "top_values": {"TS-21610": 6, "ES-14080": 5, "BD-1770": 5, "TS-11430": 4, "KL-16645": 4}}, "Customer Name": {"unique_count": 44, "top_values": {"Troy Staebel": 6, "Erin Smith": 5, "Bryan Davis": 5, "Ken Lonsdale": 4, "Evan Henry": 4}}, "Segment": {"unique_count": 3, "top_values": {"Consumer": 48, "Corporate": 34, "Home Office": 8}}, "City": {"unique_count": 41, "top_values": {"Paraparaumu": 6, "Yunyang": 5, "Marrakech": 5, "Dhaka": 4, "Barcelona": 4}}, "State": {"unique_count": 38, "top_values": {"Wellington": 8, "Henan": 5, "Marrakech-Tensift-El Haouz": 5, "California": 5, "Dhaka": 4}}, "Country": {"unique_count": 22, "top_values": {"United States": 12, "China": 9, "France": 9, "New Zealand": 8, "Germany": 7}}, "Market": {"unique_count": 6, "top_values": {"APAC": 28, "EU": 26, "Africa": 13, "US": 12, "LATAM": 6}}, "Region": {"unique_count": 11, "top_values": {"Central": 23, "Africa": 13, "Oceania": 11, "South": 10, "North Asia": 9}}, "Product ID": {"unique_count": 90, "top_values": {"FUR-BO-10003913": 1, "OFF-PA-10000350": 1, "TEC-ENE-10002254": 1, "OFF-EN-10004597": 1, "OFF-BI-10003676": 1}}, "Category": {"unique_count": 3, "top_values": {"Office Supplies": 57, "Technology": 18, "Furniture": 15}}, "Sub-Category": {"unique_count": 17, "top_values": {"Binders": 15, "Art": 11, "Storage": 8, "Paper": 7, "Labels": 5}}, "Product Name": {"unique_count": 87, "top_values": {"Sanford Pencil Sharpener, Water Color": 2, "Wilson Jones Hole Reinforcements, Economy": 2, "Eaton Parchment Paper, 8.5 x 11": 2, "Safco Stackable Bookrack, Pine": 1, "Acme Box Cutter, High Speed": 1}}, "Order Priority": {"unique_count": 4, "top_values": {"Medium": 49, "High": 30, "Critical": 7, "Low": 4}}}